Opacify-0.3.2.dist-info/DESCRIPTION.rst
Opacify-0.3.2.dist-info/METADATA
Opacify-0.3.2.dist-info/RECORD
Opacify-0.3.2.dist-info/WHEEL
Opacify-0.3.2.dist-info/entry_points.txt
Opacify-0.3.2.dist-info/metadata.json
Opacify-0.3.2.dist-info/top_level.txt
opacify/__init__.py
opacify/opacify.py
opacify/opacify_cli.py
opacify/opacifyinfo.py
opacify/progress.py
opacify/reddit.py
