Metadata-Version: 2.0
Name: Opacify
Version: 0.3.2
Summary: UNKNOWN
Home-page: https://github.com/mtingers/opacify
Author: Matth Ingersoll
Author-email: matth@mtingers.com
License: BSD 2-Clause License
Platform: UNKNOWN
Classifier: Development Status :: 4 - Beta
Classifier: Intended Audience :: Developers
Classifier: Topic :: System :: Archiving :: Mirroring
Classifier: License :: OSI Approved :: BSD License
Classifier: Programming Language :: Python :: 2.7
Classifier: Programming Language :: Python :: 3
Classifier: Programming Language :: Python :: 3.4
Classifier: Programming Language :: Python :: 3.5
Classifier: Programming Language :: Python :: 3.6
Requires-Dist: enum34
Requires-Dist: requests
